openapi_cli_generator/__init__.py
openapi_cli_generator/cli.py
openapi_cli_generator/config.py
openapi_cli_generator/generator.py
openapi_cli_generator/parser.py
tests/__init__.py
tests/conftest.py
openapi_cli_generator-0.2.0.dist-info/METADATA
openapi_cli_generator-0.2.0.dist-info/WHEEL
openapi_cli_generator-0.2.0.dist-info/entry_points.txt
openapi_cli_generator-0.2.0.dist-info/top_level.txt
openapi_cli_generator-0.2.0.dist-info/RECORD
