Metadata-Version: 2.1
Name: openapi-cli-generator
Version: 0.2.0
Summary: A command line utility to turn any OpenAPIv3 API into a Python CLI
Home-page: https://github.com/nirabo/openapi-cli-generator
Author: Lyuboslav Petrov
Author-email: petrov.lyuboslav.work@gmail.com
Classifier: Development Status :: 3 - Alpha
Classifier: Intended Audience :: Developers
Classifier: Topic :: Software Development :: Build Tools
Classifier: Programming Language :: Python :: 3
Classifier: Programming Language :: Python :: 3.7
Classifier: Programming Language :: Python :: 3.8
Classifier: Programming Language :: Python :: 3.9
Classifier: Programming Language :: Python :: 3.10
Classifier: Programming Language :: Python :: 3.11
Classifier: License :: OSI Approved :: MIT License
Classifier: Operating System :: OS Independent
Requires-Python: >=3.7
Requires-Dist: pyyaml>=6.0.2
Requires-Dist: requests>=2.32.3
Requires-Dist: openapi-spec-validator>=0.7.1
Requires-Dist: click>=8.1.3
Provides-Extra: test
Requires-Dist: pytest>=8.3.4; extra == "test"
Requires-Dist: pytest-mock>=3.14.0; extra == "test"
Requires-Dist: pytest-cov>=6.0.0; extra == "test"
Requires-Dist: requests-mock>=1.12.0; extra == "test"
Requires-Dist: coverage>=7.6.9; extra == "test"
Requires-Dist: flake8>=6.0.0; extra == "test"
Requires-Dist: pre-commit>=4.0.1; extra == "test"
Provides-Extra: dev
Requires-Dist: pytest>=8.3.4; extra == "dev"
Requires-Dist: pytest-cov>=6.0.0; extra == "dev"
Requires-Dist: flake8>=6.0.0; extra == "dev"
Requires-Dist: black>=23.0.0; extra == "dev"
Requires-Dist: mypy>=1.0.0; extra == "dev"
Requires-Dist: sphinx>=7.0.0; extra == "dev"
